pypants/__init__.py
pypants/cli.py
pypants/config.py
pypants/exceptions.py
pypants/process_packages.py
pypants/requirements.py
pypants/util.py
pypants/build_targets/__init__.py
pypants/build_targets/base.py
pypants/build_targets/behave_.py
pypants/build_targets/binary.py
pypants/build_targets/lambda_function.py
pypants/build_targets/library.py
pypants/build_targets/migration.py
pypants/build_targets/py2sfn_project.py
pypants/build_targets/python_package.py
pypants/build_targets/requirement.py
pypants/build_targets/test.py
pypants/generators/__init__.py
pypants/generators/base.py
pypants/generators/load.py
pypants-2.1.1.dist-info/entry_points.txt
pypants-2.1.1.dist-info/LICENSE.md
pypants-2.1.1.dist-info/WHEEL
pypants-2.1.1.dist-info/METADATA
pypants-2.1.1.dist-info/RECORD
