Metadata-Version: 2.1
Name: pypants
Version: 2.1.1
Summary: CLI for working with Python packages and BUILD files in a Pants monorepo
Home-page: https://github.com/NarrativeScience/pypants
License: BSD-3-Clause
Keywords: pants
Author: Jonathan Drake
Author-email: jdrake@narrativescience.com
Requires-Python: >=3.6,<4
Classifier: Intended Audience :: Developers
Classifier: License :: OSI Approved :: BSD License
Classifier: Programming Language :: Python :: 3
Classifier: Topic :: Software Development :: Libraries :: Python Modules
Requires-Dist: astor<1,>=0.7.1
Requires-Dist: black==19.3b0
Requires-Dist: Click>=7.0
Requires-Dist: cookiecutter==1.7.0
Requires-Dist: networkx<3,>=2.2
Requires-Dist: python-slugify<2,>=1.2.0
